{"1":"1141","2":"834","3":"0","4":"248","5":"502","6":"84","7":"502","8":"248","9":"6","10":"744","11":"0","12":"0","13":"82","14":"2","15":"26","16":"24","17":"582","18":"8","19":"4","20":"0","21":"3","22":"5","23":"0","24":"2","25":"1","26":"5","tikName":" Корсаковская","tikHref":"region/izbirkom?action=show&root=1000220&tvd=2652000585062&vrn=100100225883172&prver=0&pronetvd=null&region=65&sub_region=65&type=242&report_mode=null","uikName":" УИК №65","uikHref":"region/izbirkom?action=show&root=652000011&tvd=4654004274327&vrn=100100225883172&prver=0&pronetvd=null&region=65&sub_region=65&type=242&report_mode=null"}