{"1":"2496","2":"2100","3":"331","4":"728","5":"88","6":"953","7":"419","8":"728","9":"27","10":"1120","11":"0","12":"0","13":"223","14":"11","15":"83","16":"82","17":"559","18":"69","19":"3","20":"3","21":"12","22":"14","23":"6","24":"6","25":"12","26":"37","tikName":" Охинская","tikHref":"region/izbirkom?action=show&root=1000220&tvd=2652000585065&vrn=100100225883172&prver=0&pronetvd=null&region=65&sub_region=65&type=242&report_mode=null","uikName":" УИК №133","uikHref":"region/izbirkom?action=show&root=652000014&tvd=4654009166208&vrn=100100225883172&prver=0&pronetvd=null&region=65&sub_region=65&type=242&report_mode=null"}