{"0":"2123","1":"1550","2":"0","3":"722","4":"40","5":"788","6":"40","7":"722","8":"21","9":"741","10":"0","11":"0","12":"239","13":"6","14":"7","15":"88","16":"m","17":"50","18":"5","19":"4","20":"7","21":"15","22":"3","23":"0","24":"9","25":"23","tikName":" Долинская","tikHref":"region/izbirkom?action=show&root=1000220&tvd=2652000585054&vrn=100100225883172&prver=0&pronetvd=null&region=65&sub_region=65&type=242&report_mode=null","uikName":" УИК №41","uikHref":"region/izbirkom?action=show&root=652000003&tvd=4654003183082&vrn=100100225883172&prver=0&pronetvd=null&region=65&sub_region=65&type=242&report_mode=null"}