{"0":"25","1":"25","2":"0","3":"25","4":"0","5":"0","6":"0","7":"25","8":"0","9":"25","10":"0","11":"0","12":"6","13":"0","14":"12","15":"0","16":"3","17":"2","18":"0","19":"0","20":"0","21":"0","22":"0","23":"1","24":"1","25":"0","tikName":" Невельская судовая","tikHref":"region/izbirkom?action=show&root=1000220&tvd=2652000585057&vrn=100100225883172&prver=0&pronetvd=null&region=65&sub_region=65&type=242&report_mode=null","uikName":" УИК №582","uikHref":"region/izbirkom?action=show&root=652000006&tvd=4654019139108&vrn=100100225883172&prver=0&pronetvd=null&region=65&sub_region=65&type=242&report_mode=null"}