{"0":"722","1":"600","2":"21","3":"231","4":"30","5":"318","6":"51","7":"231","8":"10","9":"72","10":"0","11":"0","12":"109","13":"1","14":"24","15":"28","16":"6","17":"11","18":"3","19":"0","20":"3","21":"11","22":"0","23":"1","24":"0","25":"16","tikName":" Охинская","tikHref":"region/izbirkom?action=show&root=1000220&tvd=2652000585065&vrn=100100225883172&prver=0&pronetvd=null&region=65&sub_region=65&type=242&report_mode=null","uikName":" УИК №130","uikHref":"region/izbirkom?action=show&root=652000014&tvd=4654009166205&vrn=100100225883172&prver=0&pronetvd=null&region=65&sub_region=65&type=242&report_mode=null"}